gligen/__init__.py
gligen/gligen_inference_box.py
gligen/inpaint_mask_func.py
gligen/trainer.py
gligen/ldm/__init__.py
gligen/ldm/util.py
gligen/ldm/models/__init__.py
gligen/ldm/models/autoencoder.py
gligen/ldm/modules/__init__.py
gligen/ldm/modules/attention.py
gligen/ldm/modules/ema.py
gligen/ldm/modules/x_transformer.py
gligen/ldm/modules/image_degradation/__init__.py
gligen/ldm/modules/image_degradation/bsrgan.py
gligen/ldm/modules/image_degradation/bsrgan_light.py
gligen/ldm/modules/image_degradation/utils_image.py
gligen/ldm/modules/losses/__init__.py
gligen/ldm/modules/losses/contperceptual.py
gligen/ldm/modules/losses/vqperceptual.py
grounding_input/__init__.py
grounding_input/keypoint_grounding_tokinzer_input.py
grounding_input/text_grounding_tokinzer_input.py
grounding_input/text_image_grounding_tokinzer_input.py
visor_gligen/__init__.py
visor_gligen/gligen_inference_box.py
visor_gligen/inpaint_mask_func.py
visor_gligen/trainer.py
visor_gligen/grounding_input/__init__.py
visor_gligen/grounding_input/keypoint_grounding_tokinzer_input.py
visor_gligen/grounding_input/text_grounding_tokinzer_input.py
visor_gligen/grounding_input/text_image_grounding_tokinzer_input.py
visor_gligen/ldm/__init__.py
visor_gligen/ldm/util.py
visor_gligen/ldm/models/__init__.py
visor_gligen/ldm/models/autoencoder.py
visor_gligen/ldm/models/diffusion/__init__.py
visor_gligen/ldm/models/diffusion/classifier.py
visor_gligen/ldm/models/diffusion/ddim.py
visor_gligen/ldm/models/diffusion/ddpm.py
visor_gligen/ldm/models/diffusion/ldm.py
visor_gligen/ldm/models/diffusion/plms.py
visor_gligen/ldm/modules/__init__.py
visor_gligen/ldm/modules/attention.py
visor_gligen/ldm/modules/ema.py
visor_gligen/ldm/modules/x_transformer.py
visor_gligen/ldm/modules/diffusionmodules/__init__.py
visor_gligen/ldm/modules/diffusionmodules/grounding_net_example.py
visor_gligen/ldm/modules/diffusionmodules/keypoint_grounding_net.py
visor_gligen/ldm/modules/diffusionmodules/model.py
visor_gligen-1.6.dist-info/METADATA
visor_gligen-1.6.dist-info/WHEEL
visor_gligen-1.6.dist-info/top_level.txt
visor_gligen-1.6.dist-info/RECORD
